{"data":[{"symbol":"sh600210","name":"紫江企业","price":"5.080","changePrice":"-0.060","changePercent":"-1.167","open":"5.140","high":"5.140","low":"5.080","volume":133638.31,"amount":6812.6394,"tickTime":"15:00:00"},{"symbol":"sh600836","name":"界龙实业","price":"5.160","changePrice":"0.080","changePercent":"1.575","open":"5.080","high":"5.340","low":"5.040","volume":117531.94,"amount":6109.5269,"tickTime":"15:00:00"},{"symbol":"sh600880","name":"博瑞传播","price":"5.350","changePrice":"-0.050","changePercent":"-0.926","open":"5.370","high":"5.420","low":"5.310","volume":63446.61,"amount":3400.007,"tickTime":"15:00:00"},{"symbol":"sh601515","name":"东风股份","price":"9.920","changePrice":"-0.020","changePercent":"-0.201","open":"9.920","high":"9.920","low":"9.850","volume":9917.12,"amount":980.7022,"tickTime":"15:00:00"},{"symbol":"sh603729","name":"龙韵股份","price":"61.100","changePrice":"-0.120","changePercent":"-0.196","open":"60.530","high":"61.500","low":"60.080","volume":2856,"amount":1733.1013,"tickTime":"15:00:00"},{"symbol":"sz000659","name":"*ST中富","price":"3.960","changePrice":"-0.210","changePercent":"-5.036","open":"4.130","high":"4.150","low":"3.960","volume":299812.06,"amount":12031.6023,"tickTime":"15:29:03"},{"symbol":"sz000673","name":"当代东方","price":"13.530","changePrice":"0.280","changePercent":"2.113","open":"13.250","high":"13.600","low":"12.950","volume":63988.17,"amount":8454.5336,"tickTime":"15:29:03"},{"symbol":"sz000812","name":"陕西金叶","price":"0.000","changePrice":"0.000","changePercent":"0.000","open":"0.000","high":"0.000","low":"0.000","volume":0,"amount":0,"tickTime":"15:29:03"},{"symbol":"sz002117","name":"东港股份","price":"18.710","changePrice":"0.310","changePercent":"1.685","open":"18.350","high":"18.880","low":"18.350","volume":35166.99,"amount":6574.7148,"tickTime":"15:29:03"},{"symbol":"sz002191","name":"劲嘉股份","price":"8.850","changePrice":"-0.140","changePercent":"-1.557","open":"8.990","high":"9.040","low":"8.840","volume":83137.79,"amount":7419.5766,"tickTime":"15:29:03"},{"symbol":"sz002228","name":"合兴包装","price":"4.230","changePrice":"0.000","changePercent":"0.000","open":"4.220","high":"4.240","low":"4.210","volume":25150.51,"amount":1062.9628,"tickTime":"15:29:03"},{"symbol":"sz002229","name":"鸿博股份","price":"9.770","changePrice":"0.170","changePercent":"1.771","open":"9.600","high":"9.860","low":"9.580","volume":54331.2,"amount":5276.6646,"tickTime":"15:29:03"},{"symbol":"sz002374","name":"丽鹏股份","price":"5.060","changePrice":"-0.010","changePercent":"-0.197","open":"5.050","high":"5.100","low":"5.020","volume":34596.24,"amount":1750.7724,"tickTime":"15:29:03"},{"symbol":"sz002400","name":"省广股份","price":"5.830","changePrice":"-0.130","changePercent":"-2.181","open":"5.850","high":"6.040","low":"5.800","volume":856934.16,"amount":50632.4946,"tickTime":"15:29:03"},{"symbol":"sz002599","name":"盛通股份","price":"11.910","changePrice":"-0.050","changePercent":"-0.418","open":"11.880","high":"11.980","low":"11.780","volume":11705.99,"amount":1389.5338,"tickTime":"15:29:03"},{"symbol":"sz002701","name":"奥瑞金","price":"6.070","changePrice":"0.000","changePercent":"0.000","open":"6.050","high":"6.100","low":"6.050","volume":46837.59,"amount":2847.9776,"tickTime":"15:29:03"},{"symbol":"sz002752","name":"昇兴股份","price":"10.590","changePrice":"-0.340","changePercent":"-3.111","open":"10.930","high":"10.930","low":"10.530","volume":45869.95,"amount":4896.9994,"tickTime":"15:29:03"},{"symbol":"sz300057","name":"万顺股份","price":"9.980","changePrice":"-0.050","changePercent":"-0.499","open":"10.080","high":"10.100","low":"9.970","volume":6001,"amount":600.2133,"tickTime":"15:29:03"},{"symbol":"sz300058","name":"蓝色光标","price":"7.700","changePrice":"0.700","changePercent":"10.000","open":"7.490","high":"7.700","low":"7.350","volume":1724921.24,"amount":131760.535,"tickTime":"15:29:03"},{"symbol":"sz300071","name":"华谊嘉信","price":"0.000","changePrice":"0.000","changePercent":"0.000","open":"0.000","high":"0.000","low":"0.000","volume":0,"amount":0,"tickTime":"15:29:03"}]}